geo_places/__init__.py
geo_places/dataset.py
geo_places/loader.py
geo_places/population.py
geo_places/scraper.py
geo_places/utils.py
geo_places/elasticsearch/__init__.py
geo_places/elasticsearch/documents.py
geo_places/elasticsearch/handler.py
geo_places-0.0.4.data/data/data/municipality_population.csv
geo_places-0.0.4.dist-info/METADATA
geo_places-0.0.4.dist-info/WHEEL
geo_places-0.0.4.dist-info/top_level.txt
geo_places-0.0.4.dist-info/RECORD
