Metadata-Version: 2.1
Name: geo-places
Version: 0.0.4
Summary: A bunch of utilities for working with czech municipalities
Home-page: https://github.com/bauerji/geo_locations.git
Author: Jiri Bauer
Author-email: baueji@gmail.com
License: MIT
Platform: UNKNOWN
Classifier: License :: OSI Approved :: MIT License
Classifier: Programming Language :: Python :: 3
Classifier: Programming Language :: Python :: 3.7
Requires-Python: >=3.7
Requires-Dist: aiohttp (~=3.6.2)
Requires-Dist: beautifulsoup4 (~=4.8.1)
Requires-Dist: elasticsearch-dsl (~=7.0.0)
Requires-Dist: certifi
